jupyter_installer.py
jupyter_installer-1.0.1.dist-info/LICENSE
jupyter_installer-1.0.1.dist-info/WHEEL
jupyter_installer-1.0.1.dist-info/METADATA
jupyter_installer-1.0.1.dist-info/RECORD
